pyroll/profile_bulging/__init__.py
pyroll/profile_bulging/symmetric_roll_pass.py
pyroll_profile_bulging-3.0.0.dist-info/METADATA
pyroll_profile_bulging-3.0.0.dist-info/WHEEL
pyroll_profile_bulging-3.0.0.dist-info/licenses/LICENSE
pyroll_profile_bulging-3.0.0.dist-info/RECORD
