Metadata-Version: 2.3
Name: pyroll-profile-bulging
Version: 3.0.0
Summary: Plugin for PyRolL to model the bulging of profiles after rolling.
Project-URL: Homepage, https://pyroll.readthedocs.io
Project-URL: Repository, https://github.com/pyroll-project/pyroll-profile-rounding
Project-URL: Documentation, https://github.com/pyroll-project/pyroll-profile-rounding/blob/main/docs/docs.pdf
Author-email: Christoph Renzing <christoph.renzing@imf.tu-freiberg.de>
License: BSD-3-Clause
Classifier: Development Status :: 5 - Production/Stable
Classifier: Framework :: Hatch
Classifier: Framework :: IPython
Classifier: Framework :: Jupyter
Classifier: Framework :: Pytest
Classifier: Framework :: Sphinx
Classifier: Intended Audience :: Manufacturing
Classifier: Intended Audience :: Science/Research
Classifier: License :: OSI Approved :: BSD License
Classifier: Natural Language :: English
Classifier: Operating System :: OS Independent
Classifier: Programming Language :: Python :: 3
Classifier: Programming Language :: Python :: 3.9
Classifier: Programming Language :: Python :: 3.10
Classifier: Programming Language :: Python :: 3.11
Classifier: Topic :: Scientific/Engineering
Requires-Python: <4.0,>=3.9
Requires-Dist: pyroll-core~=3.0dev1
